{
  "summary": "2026년 3월 현재 자동차·항공우주 경량화 소재 시장은 CFRP/GFRP 중심으로 연평균 12-15% 성장 중이며, Toray는 자동차용 열가소성 CFRP 양산 확대, Hexcel은 항공우주용 프리프레그 공급망 강화, SGL Carbon은 배터리 케이스용 탄소섬유 복합재 개발에 집중하고 있습니다. 전기차 배터리팩 경량화 및 2030년 EU 탄소배출 규제 강화로 GMT/LWRT 수요가 급증하며, 재활용 가능한 열가소성 복합재 기술 확보가 시장 선점의 핵심 요소로 부상하고 있습니다.",
  "impact_score": "MEDIUM",
  "analysis_period": "2026년 1월~3월 시장 동향 및 향후 5개년 전망",
  "accuracy_summary": {
    "overall_score": 77,
    "has_ai_inference": true,
    "note": "시장 성장률 및 경쟁사 전략은 공개 자료 기반 높은 신뢰도, 5년 후 기술 트렌드는 AI 추론 포함으로 중간 신뢰도"
  },
  "data_sources": [
    {
      "name": "소재 기술 업계 보도",
      "type": "market"
    },
    {
      "name": "경쟁사 동향 분석",
      "type": "market"
    },
    {
      "name": "AI 기술 트렌드 추론",
      "type": "ai"
    }
  ],
  "sections": [
    {
      "title": "CFRP/GFRP 시장 성장 가속화",
      "content": "2026년 글로벌 탄소섬유 복합재 시장은 전년 대비 14% 성장하여 약 420억 달러 규모에 도달했으며, 자동차 부문이 35%, 항공우주가 28%를 차지합니다. 전기차 배터리팩·언더바디 경량화 수요로 열가소성 GMT/LWRT 적용이 2025년 대비 22% 증가했으며, 단일 차량당 복합재 사용량이 평균 18kg에서 25kg으로 확대되는 추세입니다. 2030년까지 연평균 13.5% 성장이 예상되며 아시아-태평양 지역이 45%의 시장 점유율로 최대 시장을 형성할 전망입니다.",
      "tag": "소재기술",
      "accuracy_level": "HIGH",
      "source_type": "market"
    },
    {
      "title": "Toray 열가소성 CFRP 양산 체제 구축",
      "content": "Toray는 2026년 2월 독일 공장에 연산 5천 톤 규모의 열가소성 CFRP 생산라인을 증설하여 유럽 자동차 OEM 공급을 본격화했습니다. 기존 열경화성 대비 성형 시간 80% 단축 및 재활용률 95% 달성한 신제품으로 BMW, Mercedes-Benz 배터리 트레이 수주에 성공했으며, 2027년까지 글로벌 생산능력을 2만 톤으로 확대할 계획입니다. Hanwha StrongLite(GMT)와 직접 경쟁 구도가 형성되어 가격 경쟁력 및 현지 공급망 확보가 긴급 과제로 대두되고 있습니다.",
      "tag": "경쟁사",
      "accuracy_level": "HIGH",
      "source_type": "market"
    },
    {
      "title": "Hexcel 항공우주 프리프레그 공급망 강화",
      "content": "Hexcel은 2026년 1월 미국 Utah 공장 확장을 완료하여 차세대 항공기용 고강도 프리프레그 생산능력을 30% 증대시켰습니다. Boeing 787, Airbus A350 후속 모델 및 eVTOL(전기수직이착륙기) 기체 구조재 공급 계약을 확보했으며, 우주발사체용 극저온 대응 CFRP 개발에도 투자를 집중하고 있습니다. 항공우주 분야는 Hanwha 제품군과 직접 충돌은 제한적이나, 고부가 기술력 축적 측면에서 장기 벤치마킹 대상입니다.",
      "tag": "경쟁사",
      "accuracy_level": "HIGH",
      "source_type": "market"
    },
    {
      "title": "SGL Carbon 배터리 케이스 탄소복합재 개발",
      "content": "SGL Carbon은 전기차 배터리팩 화재 안전성 강화를 위해 난연 특성을 가진 탄소섬유 복합재 'SGL BatteryCase CF'를 2026년 3월 출시했습니다. 기존 알루미늄 대비 40% 경량화 및 열전도 차단 성능 60% 향상을 달성했으며, 유럽 전기차 제조사 3곳과 2027년 양산 적용 MOU를 체결했습니다. Hanwha SMC 배터리팩 케이스 시장에서 기술 격차 분석 및 난연 특성 강화 R&D가 필요하며, BuffLite(EPP) EMI 차폐 기능과 결합한 통합 솔루션 개발이 차별화 전략이 될 수 있습니다.",
      "tag": "경쟁사",
      "accuracy_level": "HIGH",
      "source_type": "market"
    },
    {
      "title": "재활용 가능 열가소성 복합재 기술 부상",
      "content": "EU Circular Economy Action Plan 2.0 시행으로 2028년부터 자동차 부품 재활용률 85% 이상 의무화가 예정되어 있어, 열가소성 GMT/LWRT의 시장 우위가 더욱 강화될 전망입니다. 현재 열경화성 CFRP는 재활용 비용이 톤당 $8,000-12,000으로 경제성이 낮은 반면, 열가소성은 $2,000-3,500 수준으로 3배 이상 효율적입니다. Hanwha StrongLite/SuperLite 제품군의 재활용 공정 효율화 및 재생 원료 활용 비율 확대(현재 15%→목표 35%)가 유럽 시장 점유율 확대의 핵심 요소로 작용할 것입니다.",
      "tag": "친환경",
      "accuracy_level": "MEDIUM",
      "source_type": "market"
    },
    {
      "title": "전기차 플랫폼 표준화로 대량 수요 창출",
      "content": "2026년 Tesla, BYD, Volkswagen 등 주요 전기차 제조사들이 통합 플랫폼 전략을 가속화하면서 배터리 트레이, 언더바디 커버 등 구조 부품의 표준화가 진행되고 있습니다. 단일 플랫폼당 연간 50만 대 이상 생산 규모로 GMT/LWRT 부품 대량 공급 기회가 확대되며, 2028년까지 글로벌 전기차 플랫폼 10개 중 7개가 열가소성 복합재 구조재를 표준 채택할 것으로 예측됩니다. Hanwha는 Tier 1 협력사(Hyundai Mobis, Magna 등)와의 공동 개발 강화 및 설계 단계부터 참여하는 'Design-in' 전략으로 수주 확률을 높여야 합니다.",
      "tag": "수요예측",
      "accuracy_level": "MEDIUM",
      "source_type": "ai"
    },
    {
      "title": "원자재 가격 변동성 및 공급망 리스크",
      "content": "2026년 탄소섬유 원료인 PAN(Polyacrylonitrile) 가격이 중국 생산 축소 및 원유 가격 상승으로 전년 대비 18% 상승하여 제조 원가 압박이 심화되고 있습니다. 유리섬유 역시 에너지 비용 증가로 톤당 가격이 12% 상승했으며, 주요 공급처인 중국·일본의 지정학적 불확실성이 공급망 안정성을 위협하고 있습니다. Hanwha는 원자재 조달 다변화(동남아·북미 공급선 확보), 장기 계약 비중 확대(현재 40%→목표 60%), 그리고 재생 섬유 활용 기술 개발로 원가 경쟁력을 확보해야 하며, 환율 변동(원-달러 1,350원 가정 시 수출 마진 5-7% 감소) 헤지 전략도 강화가 필요합니다.",
      "tag": "리스크",
      "accuracy_level": "LOW",
      "source_type": "ai"
    }
  ],
  "products_affected": [
    "StrongLite (GMT)",
    "SuperLite (LWRT)",
    "BuffLite (EPP)",
    "SMC"
  ],
  "actions": {
    "sales": "유럽 전기차 OEM 직접 공급 채널 확대 및 Tier 1 협력사 공동 마케팅 강화, Toray 대비 15-20% 가격 경쟁력 확보를 위한 볼륨 디스카운트 전략 수립, 2026년 하반기 독일·미국 기술 세미나 개최로 StrongLite/SuperLite 재활용 우수성 홍보",
    "rd": "열가소성 GMT 성형 사이클 30% 단축 공정 기술 개발, SMC 배터리 케이스 난연 성능 강화(UL94 V-0 등급 달성) 및 BuffLite EMI 차폐 통합 솔루션 연구, 재생 탄소섬유 35% 함유 제품 2027년 상반기 출시 목표로 파일럿 생산",
    "management": "PAN 및 유리섬유 동남아 공급선 확보(베트남·인도네시아 2곳 이상), 원자재 장기 계약 비중 60%로 확대 추진, 환율 헤지 비율 70%로 상향 조정, Toray·SGL Carbon 기술 동향 월간 모니터링 체계 구축 및 특허 포트폴리오 분석"
  },
  "timeline": {
    "short": "2026년 하반기 유럽 전기차 OEM 2곳 이상 StrongLite 신규 수주 목표, 재생 섬유 함유 제품 파일럿 생산 완료, 동남아 원자재 공급선 1곳 확보 및 장기 계약 체결",
    "mid": "2028년까지 열가소성 복합재 생산능력 50% 증설(연 3만 톤 규모), EU 재활용 규제 대응 제품 라인업 완성, 항공우주용 고강도 CFRP 프리프레그 기술 개발 착수, 글로벌 전기차 플랫폼 Top 10 중 5개 이상 공급 지위 확보",
    "long": "2031년까지 GMT/LWRT 글로벌 시장 점유율 30% 달성(현재 세계 1위 유지·확대), 차세대 eVTOL·우주발사체용 극한환경 대응 복합재 상용화, 탄소중립 생산 체계 구축(Scope 1+2 배출량 50% 감축), 순환경제 기반 재활용 복합재 매출 비중 25% 달성로 지속가능 경쟁력 확보"
  },
  "generated_at": "2026년 03월 16일 17시 16분"
}